odoo/addons/website_odoo_debranding/README.rst
odoo/addons/website_odoo_debranding/__init__.py
odoo/addons/website_odoo_debranding/__manifest__.py
odoo/addons/website_odoo_debranding/hooks.py
odoo/addons/website_odoo_debranding/i18n/es_AR.po
odoo/addons/website_odoo_debranding/i18n/it.po
odoo/addons/website_odoo_debranding/i18n/pt_BR.po
odoo/addons/website_odoo_debranding/i18n/tr.po
odoo/addons/website_odoo_debranding/i18n/website_odoo_debranding.pot
odoo/addons/website_odoo_debranding/readme/CONTRIBUTORS.md
odoo/addons/website_odoo_debranding/readme/DESCRIPTION.md
odoo/addons/website_odoo_debranding/readme/USAGE.md
odoo/addons/website_odoo_debranding/static/description/icon.png
odoo/addons/website_odoo_debranding/static/description/index.html
odoo/addons/website_odoo_debranding/templates/disable_odoo.xml
odoo/addons/website_odoo_debranding/tests/__init__.py
odoo/addons/website_odoo_debranding/tests/test_dummy.py
odoo_addon_website_odoo_debranding-18.0.1.0.0.5.dist-info/METADATA
odoo_addon_website_odoo_debranding-18.0.1.0.0.5.dist-info/WHEEL
odoo_addon_website_odoo_debranding-18.0.1.0.0.5.dist-info/top_level.txt
odoo_addon_website_odoo_debranding-18.0.1.0.0.5.dist-info/RECORD
